{
  "delivery": [
    {
      "id": 2,
      "name": "Casa de comida 2",
      "address": "Palermo Hollywood",
      "phone": "2222222"
    },
    {
      "id": 3,
      "name": "Casa de comida 3",
      "address": "Belgrano",
      "phone": "3333333"
    },
    {
      "id": 4,
      "name": "Casa de comida 4",
      "address": "Boedo",
      "phone": "1111111"
    },
    {
      "id": 5,
      "name": "Casa de comida 5",
      "address": "Caballito",
      "phone": "2222222"
    },
    {
      "id": 6,
      "name": "Casa de comida 6",
      "address": "Almagro",
      "phone": "3333333"
    },
    {
      "id": 7,
      "name": "Casa de comida 7",
      "address": "Belgrano",
      "phone": "3333333"
    },
    {
      "id": 8,
      "name": "Casa de comida 8",
      "address": "Boedo",
      "phone": "1111111"
    },
    {
      "id": 9,
      "name": "Casa de comida 9",
      "address": "Caballito",
      "phone": "2222222"
    },
    {
      "id": 10,
      "name": "Casa de comida 10",
      "address": "Almagro",
      "phone": "3333333"
    },
    {
      "id": 11,
      "name": "Casa de comida 11",
      "address": "Palermo Soho",
      "phone": "1111111"
    },
    {
      "id": 12,
      "name": "Casa de comida 12",
      "address": "Palermo Hollywood",
      "phone": "2222222"
    },
    {
      "id": 13,
      "name": "Casa de comida 13",
      "address": "Belgrano",
      "phone": "3333333"
    },
    {
      "id": 14,
      "name": "Casa de comida 14",
      "address": "Boedo",
      "phone": "1111111"
    },
    {
      "id": 15,
      "name": "Casa de comida 15",
      "address": "Caballito",
      "phone": "2222222"
    },
    {
      "id": 16,
      "name": "Casa de comida 16",
      "address": "Almagro",
      "phone": "3333333"
    },
    {
      "id": 17,
      "name": "Casa de comida 17",
      "address": "Belgrano",
      "phone": "3333333"
    },
    {
      "secret": "I'm hidden!",
      "name": "frrfrrfr",
      "phone": "rffrfrrf",
      "description": "rfrfrffrrf",
      "address": "3ee33e3",
      "schedule_init": "02:20",
      "lastname": "rffrrfrfrf",
      "email": "cedenoabraham@gmail.com",
      "id": 19
    },
    {
      "secret": "I'm hidden!",
      "name": "Romina",
      "phone": "1156458978",
      "description": "Empanadas Tucumanas y Pizza",
      "specialty": "Carne Suave\nCarne Dulce",
      "address": "Mario Bravo 1020",
      "schedule_init": "02:21",
      "lastname": "Gunter",
      "email": "romina@gmail.com",
      "id": 20
    },
    {
      "name": "EL Rincon Norteño Tucuhuehd",
      "phone": "12345678",
      "description": "Empanadas tucumanas ",
      "specialty": "Carne suave",
      "address": "belgrano",
      "schedule_init": "02:02",
      "schedule_end": "02:02",
      "main_commercial_contact_name": "Ana",
      "main_commercial_contact_lastname": "Lugo",
      "main_commercial_contact_phone": "11223344",
      "main_commercial_contact_email": "ana@gmail.com",
      "other_commercial_contact_name": "a",
      "other_commercial_contact_lastname": "b",
      "other_commercial_contact_phone": "c",
      "other_commercial_contact_email": "d@d.com",
      "id": 21
    }
  ]
}